./.gitignore
./.hadolint.yaml
./LICENSE
./MANIFEST.in
./PKG-INFO
./README.md
./__init__.py
./mcp_ableton_server.py
./osc_daemon.py
./pyproject.toml
./uv.lock
ableton_live_mcp_server-0.2.1.dist-info/METADATA
ableton_live_mcp_server-0.2.1.dist-info/WHEEL
ableton_live_mcp_server-0.2.1.dist-info/entry_points.txt
ableton_live_mcp_server-0.2.1.dist-info/licenses/LICENSE
ableton_live_mcp_server-0.2.1.dist-info/RECORD
