Metadata-Version: 2.4
Name: ableton-live-mcp-server
Version: 0.2.1
Summary: MCP Server for Ableton Live
Project-URL: Homepage, https://github.com/mrmos/ableton-live-mcp-server
Project-URL: Issues, https://github.com/mrmos/ableton-live-mcp-server/issues
Author: Project Contributors
License: MIT License
License-File: LICENSE
Classifier: Development Status :: 3 - Alpha
Classifier: Intended Audience :: Developers
Classifier: License :: OSI Approved :: MIT License
Classifier: Programming Language :: Python :: 3
Classifier: Programming Language :: Python :: 3.8
Classifier: Programming Language :: Python :: 3.9
Classifier: Programming Language :: Python :: 3.10
Classifier: Programming Language :: Python :: 3.11
Requires-Python: >=3.10
Requires-Dist: fastmcp>=0.4.1
Requires-Dist: mcp>=1.4.0
Requires-Dist: python-osc
Requires-Dist: uvicorn
